hypz.py
hypz_sdk-2.1.0.dist-info/METADATA
hypz_sdk-2.1.0.dist-info/WHEEL
hypz_sdk-2.1.0.dist-info/top_level.txt
hypz_sdk-2.1.0.dist-info/RECORD
