Metadata-Version: 2.1
Name: hypz-sdk
Version: 2.1.0
Summary: Official Python SDK for Hypz Cloud Storage - Store, manage, and serve files with a simple API
Home-page: https://github.com/ysr-hameed/hypz
Author: Hypz Team
Author-email: support@hypz.io
License: MIT
Project-URL: Documentation, https://hypz.io/docs
Project-URL: Source, https://github.com/ysr-hameed/hypz
Project-URL: Tracker, https://github.com/ysr-hameed/hypz/issues
Keywords: hypz cloud-storage file-storage s3 cdn upload storage files api sdk backblaze b2
Classifier: Development Status :: 5 - Production/Stable
Classifier: Intended Audience :: Developers
Classifier: Topic :: Software Development :: Libraries :: Python Modules
Classifier: License :: OSI Approved :: MIT License
Classifier: Programming Language :: Python :: 3
Classifier: Programming Language :: Python :: 3.7
Classifier: Programming Language :: Python :: 3.8
Classifier: Programming Language :: Python :: 3.9
Classifier: Programming Language :: Python :: 3.10
Classifier: Programming Language :: Python :: 3.11
Classifier: Programming Language :: Python :: 3.12
Requires-Python: >=3.7
Requires-Dist: requests >=2.25.0
Provides-Extra: dev
Requires-Dist: black >=21.0 ; extra == 'dev'
Requires-Dist: flake8 >=3.9 ; extra == 'dev'
Requires-Dist: pytest >=6.0 ; extra == 'dev'
